hsp2/__init__.py
hsp2/hsp2/ADCALC.py
hsp2/hsp2/ATEMP.py
hsp2/hsp2/CONS.py
hsp2/hsp2/COPY.py
hsp2/hsp2/GENER.py
hsp2/hsp2/GQUAL.py
hsp2/hsp2/HTRCH.py
hsp2/hsp2/HYDR.py
hsp2/hsp2/IQUAL.py
hsp2/hsp2/IWATER.py
hsp2/hsp2/IWTGAS.py
hsp2/hsp2/NUTRX_Class.py
hsp2/hsp2/OXRX_Class.py
hsp2/hsp2/PHCARB_Class.py
hsp2/hsp2/PLANK_Class.py
hsp2/hsp2/PQUAL.py
hsp2/hsp2/PSTEMP.py
hsp2/hsp2/PWATER.py
hsp2/hsp2/PWTGAS.py
hsp2/hsp2/RQUAL.py
hsp2/hsp2/RQUAL_Class.py
hsp2/hsp2/RQUTIL.py
hsp2/hsp2/SEDMNT.py
hsp2/hsp2/SEDTRN.py
hsp2/hsp2/SNOW.py
hsp2/hsp2/SOLIDS.py
hsp2/hsp2/SPECL.py
hsp2/hsp2/__init__.py
hsp2/hsp2/configuration.py
hsp2/hsp2/main.py
hsp2/hsp2/mainDoE.py
hsp2/hsp2/om.py
hsp2/hsp2/om_model_linkage.py
hsp2/hsp2/om_model_object.py
hsp2/hsp2/om_sim_timer.py
hsp2/hsp2/om_special_action.py
hsp2/hsp2/state.py
hsp2/hsp2/state_fn_defaults.py
hsp2/hsp2/uci.py
hsp2/hsp2/utilities.py
hsp2/hsp2io/__init__.py
hsp2/hsp2io/hdf.py
hsp2/hsp2io/io.py
hsp2/hsp2io/protocols.py
hsp2/hsp2tools/HBNOutput.py
hsp2/hsp2tools/HDF5.py
hsp2/hsp2tools/HSP2_CLI.py
hsp2/hsp2tools/SegmentExpander.py
hsp2/hsp2tools/__init__.py
hsp2/hsp2tools/clone.py
hsp2/hsp2tools/commands.py
hsp2/hsp2tools/fetch.py
hsp2/hsp2tools/graph.py
hsp2/hsp2tools/readCSV.py
hsp2/hsp2tools/readHBN.py
hsp2/hsp2tools/readUCI.py
hsp2/hsp2tools/readWDM.py
hsp2/hsp2tools/restart.py
hsp2/hsp2tools/data/HBNAliases.csv
hsp2/hsp2tools/data/ParseTable.csv
hsp2/hsp2tools/data/SaveTable.csv
hsp2/hsp2tools/data/rename.csv
hsp2-0.11.0a1.dist-info/LICENSE
hsp2-0.11.0a1.dist-info/METADATA
hsp2-0.11.0a1.dist-info/WHEEL
hsp2-0.11.0a1.dist-info/entry_points.txt
hsp2-0.11.0a1.dist-info/top_level.txt
hsp2-0.11.0a1.dist-info/RECORD
