Metadata-Version: 2.1
Name: hsp2
Version: 0.11.0a1
Summary: Hydrological Simulation Program - Python
Author-email: "RESPEC, Inc" <Paul.Duda@respec.com>
License: GNU AFFERO GENERAL PUBLIC LICENSE
Project-URL: documentation, http://www.respec.com/product/hydrologic-simulation-program-python-hsp%C2%B2/
Project-URL: github, https://github.com/respec/HSPsquared
Keywords: hydrology,hydrological,hydraulic,hspf,simulation,python
Classifier: Development Status :: 3 - Alpha
Classifier: Intended Audience :: Science/Research
Classifier: Intended Audience :: End Users/Desktop
Classifier: Intended Audience :: Developers
Classifier: Environment :: Console
Classifier: License :: OSI Approved :: GNU Affero General Public License v3
Classifier: Natural Language :: English
Classifier: Operating System :: OS Independent
Classifier: Programming Language :: Python :: 3.9
Classifier: Programming Language :: Python :: 3.10
Classifier: Programming Language :: Python :: 3.11
Classifier: Programming Language :: Python :: 3.12
Classifier: Topic :: Scientific/Engineering
Classifier: Topic :: Software Development :: Libraries :: Python Modules
Requires-Python: >=3.9
License-File: LICENSE
Requires-Dist: cltoolbox
Requires-Dist: numba
Requires-Dist: pandas
Requires-Dist: tables
Provides-Extra: dev
Requires-Dist: hsp2[test] ; extra == 'dev'
Provides-Extra: slim
Requires-Dist: numba ; extra == 'slim'
Requires-Dist: pandas ; extra == 'slim'
Provides-Extra: test
Requires-Dist: pytest ; extra == 'test'
Requires-Dist: pytest-cov ; extra == 'test'
